hip_data_tools/__init__.py
hip_data_tools/apache/__init__.py
hip_data_tools/apache/cassandra.py
hip_data_tools/apache/kafka.py
hip_data_tools/aws/__init__.py
hip_data_tools/aws/athena.py
hip_data_tools/aws/common.py
hip_data_tools/aws/s3.py
hip_data_tools/common.py
hip_data_tools/etl/__init__.py
hip_data_tools/etl/adwords_to_athena.py
hip_data_tools/etl/adwords_to_s3.py
hip_data_tools/etl/athena_to_athena.py
hip_data_tools/etl/athena_to_dataframe.py
hip_data_tools/etl/athena_to_s3.py
hip_data_tools/etl/common.py
hip_data_tools/etl/dataframe_to_cassandra.py
hip_data_tools/etl/google_sheet_to_athena.py
hip_data_tools/etl/google_sheet_to_s3.py
hip_data_tools/etl/s3.py
hip_data_tools/etl/s3_to_dataframe.py
hip_data_tools/etl/s3_to_s3.py
hip_data_tools/google/__init__.py
hip_data_tools/google/common.py
hip_data_tools/google/sheets.py
hip_data_tools/hipages/__init__.py
hip_data_tools/hipages/version_tracking.py
hip_data_tools/oracle/mysql.py
hip_data_tools-1.70.0.dist-info/LICENSE.md
hip_data_tools-1.70.0.dist-info/METADATA
hip_data_tools-1.70.0.dist-info/WHEEL
hip_data_tools-1.70.0.dist-info/RECORD
