Metadata-Version: 2.1
Name: hip_data_tools
Version: 1.70.0
Summary: Common Python tools and utilities for data engineering.
License: OSL
Author: Hipages Data Team
Author-email: datascience@hipagesgroup.com.au
Requires-Python: >=3.11,<4
Classifier: License :: Other/Proprietary License
Classifier: Programming Language :: Python :: 3
Classifier: Programming Language :: Python :: 3.11
Classifier: Programming Language :: Python :: 3.12
Classifier: Programming Language :: Python :: 3.13
Requires-Dist: Cython (>=3.0.10,<4.0.0)
Requires-Dist: GitPython (>=3.1.31,<4.0.0)
Requires-Dist: arrow (>=1.2.3,<2.0.0)
Requires-Dist: boto3 (>=1.26.107,<2.0.0)
Requires-Dist: botocore (>=1.29.107,<2.0.0)
Requires-Dist: cassandra-driver (>=3.29.1,<4.0.0)
Requires-Dist: confluent-kafka (>=2.0.2,<3.0.0)
Requires-Dist: fastparquet (>=2023.2.0,<2024.0.0)
Requires-Dist: gspread (>=5.8.0,<6.0.0)
Requires-Dist: joblib (>=1.2.0,<2.0.0)
Requires-Dist: lxml (>=4.9.2,<5.0.0)
Requires-Dist: mysqlclient (>=2.2.4,<3.0.0)
Requires-Dist: oauth2client (>=4.1.3,<5.0.0)
Requires-Dist: pandas (>=2.1.4,<3.0.0)
Requires-Dist: pyarrow (>=16.1.0,<17.0.0)
Requires-Dist: retrying (>=1.3.4,<2.0.0)
Requires-Dist: stringcase (>=1.2.0,<2.0.0)
